helloworld.py
helloworld_JeRaMeeee_2021-0.0.1.dist-info/LICENSE.txt
helloworld_JeRaMeeee_2021-0.0.1.dist-info/METADATA
helloworld_JeRaMeeee_2021-0.0.1.dist-info/WHEEL
helloworld_JeRaMeeee_2021-0.0.1.dist-info/top_level.txt
helloworld_JeRaMeeee_2021-0.0.1.dist-info/RECORD
