Metadata-Version: 2.1
Name: helloworld-JeRaMeeee-2021
Version: 0.0.1
Summary: say hello!
Home-page: UNKNOWN
License: UNKNOWN
Platform: UNKNOWN
